ibmcloud/IBMCloud.py
ibmcloud/__init__.py
ibmcloud/test.py
ibmcloud/test_credentials.py
ibmcloud-0.1.0.dist-info/METADATA
ibmcloud-0.1.0.dist-info/WHEEL
ibmcloud-0.1.0.dist-info/top_level.txt
ibmcloud-0.1.0.dist-info/RECORD
